struid/__init__.py
struid/struid.py
struid-0.0.5.dist-info/LICENSE
struid-0.0.5.dist-info/METADATA
struid-0.0.5.dist-info/WHEEL
struid-0.0.5.dist-info/top_level.txt
struid-0.0.5.dist-info/RECORD
