Metadata-Version: 2.1
Name: struid
Version: 0.0.5
Summary: Struid - 'Stringy-UUID', an enhanced UUID package
Author-email: Dale Magee <struid@antisol.org>
Project-URL: Homepage, https://gitlab.com/AntiSol/struid
Project-URL: Bug Tracker, https://gitlab.com/AntiSol/struid/-/issues
Classifier: Development Status :: 4 - Beta
Classifier: Intended Audience :: Developers
Classifier: Programming Language :: Python :: 3
Classifier: License :: OSI Approved :: BSD License
Classifier: Operating System :: OS Independent
Requires-Python: >=3.7
License-File: LICENSE
